setup.cfg
setup.py
lovelace/__init__.py
lovelace/config.py
lovelace/utils.py
lovelace.egg-info/PKG-INFO
lovelace.egg-info/SOURCES.txt
lovelace.egg-info/dependency_links.txt
lovelace.egg-info/requires.txt
lovelace.egg-info/top_level.txt
lovelace/services/__init__.py
lovelace/services/data_access/__init__.py
lovelace/services/data_access/page_content.py
lovelace/services/data_access/page_meta.py
lovelace/services/data_access/search.py
lovelace/services/data_access/utils.py
lovelace/services/data_access/wikipedia.py
lovelace/services/parser/__init__.py
lovelace/services/parser/service.py
tests/__init__.py
tests/conftest.py
tests/data_access_tests/__init__.py
tests/data_access_tests/test_page_content.py
tests/data_access_tests/test_page_meta.py
tests/data_access_tests/test_search.py
tests/fixtures/__init__.py
tests/fixtures/page_meta.py
tests/strategies/__init__.py
tests/strategies/page_meta.py