Metadata-Version: 1.1
Name: lovelace
Version: 0.0.4
Summary: Library for asynchronous working with Wikipedia API.
Home-page: https://github.com/lycantropos/lovelace/
Author: Azat Ibrakov
Author-email: azatibrakov@gmail.com
License: UNKNOWN
Download-URL: https://github.com/lycantropos/lovelace/archive/master.tar.gz
Keywords: async wikipedia api
Platform: UNKNOWN
